defectpl/__init__.py
defectpl/cli.py
defectpl/comparepl.py
defectpl/data.py
defectpl/defectpl.mplstyle
defectpl/defectpl.py
defectpl/plot.py
defectpl/utils.py
defectpl/vibspectra1d.py
defectpl-0.1.5.dist-info/entry_points.txt
defectpl-0.1.5.dist-info/LICENSE
defectpl-0.1.5.dist-info/METADATA
defectpl-0.1.5.dist-info/WHEEL
defectpl-0.1.5.dist-info/RECORD
