Metadata-Version: 2.1
Name: defectpl
Version: 0.1.5
Summary: A unified package for optical properties of point defects.
Home-page: https://github.com/Shibu778/defectpl
License: MIT
Keywords: defects,optical properties,point defects,DFT,VASP,pymatgen
Author: Shibu Meher
Author-email: shibumeher@iisc.ac.in
Requires-Python: >=3.9,<4.0
Classifier: Development Status :: 3 - Alpha
Classifier: Intended Audience :: Science/Research
Classifier: License :: OSI Approved :: MIT License
Classifier: Operating System :: OS Independent
Classifier: Programming Language :: Python :: 3
Classifier: Programming Language :: Python :: 3.9
Classifier: Programming Language :: Python :: 3.10
Classifier: Programming Language :: Python :: 3.11
Classifier: Topic :: Scientific/Engineering :: Chemistry
Classifier: Topic :: Scientific/Engineering :: Information Analysis
Classifier: Topic :: Scientific/Engineering :: Physics
Classifier: Topic :: Software Development :: Libraries :: Python Modules
Requires-Dist: PyYAML (>=6.0.2,<7.0.0)
Requires-Dist: click (>=8.1.7,<9.0.0)
Requires-Dist: numpy (>=2.1.2,<3.0.0)
Requires-Dist: pdoc3 (>=0.11.1,<0.12.0)
Requires-Dist: pymatgen (==2024.10.3)
Project-URL: Documentation, https://Shibu778.github.io/defectpl/
Project-URL: Repository, https://github.com/Shibu778/defectpl
